sflkit/__init__.py
sflkit/cli.py
sflkit/color.py
sflkit/config.py
sflkit/evaluation.py
sflkit/logger.py
sflkit/analysis/__init__.py
sflkit/analysis/analysis_type.py
sflkit/analysis/analyzer.py
sflkit/analysis/factory.py
sflkit/analysis/mapping.py
sflkit/analysis/predicate.py
sflkit/analysis/similarity.py
sflkit/analysis/spectra.py
sflkit/analysis/suggestion.py
sflkit/events/__init__.py
sflkit/events/event_file.py
sflkit/events/mapping.py
sflkit/features/__init__.py
sflkit/features/handler.py
sflkit/features/value.py
sflkit/features/vector.py
sflkit/instrumentation/__init__.py
sflkit/instrumentation/dir_instrumentation.py
sflkit/instrumentation/file_instrumentation.py
sflkit/language/__init__.py
sflkit/language/extract.py
sflkit/language/finder.py
sflkit/language/language.py
sflkit/language/meta.py
sflkit/language/visitor.py
sflkit/language/java/__init__.py
sflkit/language/java/extract.py
sflkit/language/java/factory.py
sflkit/language/java/finder.py
sflkit/language/java/visitor.py
sflkit/language/python/__init__.py
sflkit/language/python/extract.py
sflkit/language/python/factory.py
sflkit/language/python/finder.py
sflkit/language/python/visitor.py
sflkit/model/__init__.py
sflkit/model/model.py
sflkit/model/scope.py
sflkit/runners/__init__.py
sflkit/runners/run.py
sflkit/weights/__init__.py
sflkit/weights/analyzer.py
sflkit/weights/models.py
sflkit-0.4.0.dist-info/licenses/LICENSE
sflkit-0.4.0.dist-info/METADATA
sflkit-0.4.0.dist-info/WHEEL
sflkit-0.4.0.dist-info/entry_points.txt
sflkit-0.4.0.dist-info/top_level.txt
sflkit-0.4.0.dist-info/RECORD
