Metadata-Version: 2.4
Name: sflkit
Version: 0.4.0
Summary: SFLKit: : A Workbench for Statistical Fault Localization
Author-email: Marius Smytzek <marius.smytzek@cispa.de>
License: MIT License
Project-URL: Homepage, https://github.com/smythi93/sflkit/
Project-URL: Bug Tracker, https://github.com/smythi93/sflkit/issues
Classifier: Intended Audience :: Science/Research
Classifier: Programming Language :: Python :: 3.10
Classifier: License :: OSI Approved :: MIT License
Classifier: Topic :: Scientific/Engineering
Classifier: Topic :: Software Development :: Testing
Requires-Python: >=3.10
License-File: LICENSE
Requires-Dist: sflkitlib>=0.1.1
Requires-Dist: numpy>=2.1.3
Requires-Dist: matplotlib>=3.10.0
Requires-Dist: pandas>=2.2.3
Requires-Dist: sortedcollections>=2.1.0
Requires-Dist: java-ast>=1.0.2
Provides-Extra: test
Requires-Dist: pytest>=8.3.4; extra == "test"
Requires-Dist: pytest-cov>=6.0.0; extra == "test"
Requires-Dist: pytest-html>=4.1.1; extra == "test"
Requires-Dist: pytest-rerunfailures>=15.0; extra == "test"
Requires-Dist: parameterized>=0.9.0; extra == "test"
Dynamic: license-file
